labrecipipe/__init__.py
labrecipipe/labrecipipe.py
labrecipipe-0.0.2.dist-info/METADATA
labrecipipe-0.0.2.dist-info/WHEEL
labrecipipe-0.0.2.dist-info/entry_points.txt
labrecipipe-0.0.2.dist-info/top_level.txt
labrecipipe-0.0.2.dist-info/RECORD
