Metadata-Version: 2.1
Name: labrecipipe
Version: 0.0.2
Summary: Labrecorder remote
Home-page: UNKNOWN
License: BSD 3-Clause License
Keywords: labrecorder,labstreaminglayer,xdf
Platform: UNKNOWN
Classifier: Framework :: Django
Classifier: License :: OSI Approved :: BSD License
Classifier: Programming Language :: Python :: 3
Classifier: Programming Language :: Python :: 3.6
